crossref_local/__init__.py
crossref_local/__main__.py
crossref_local/aio.py
crossref_local/api.py
crossref_local/cache.py
crossref_local/cache_export.py
crossref_local/cache_viz.py
crossref_local/citations.py
crossref_local/cli.py
crossref_local/cli_cache.py
crossref_local/cli_completion.py
crossref_local/cli_main.py
crossref_local/cli_mcp.py
crossref_local/config.py
crossref_local/db.py
crossref_local/fts.py
crossref_local/mcp_server.py
crossref_local/models.py
crossref_local/remote.py
crossref_local/server.py
crossref_local/impact_factor/__init__.py
crossref_local/impact_factor/calculator.py
crossref_local/impact_factor/journal_lookup.py
crossref_local-0.4.0.dist-info/METADATA
crossref_local-0.4.0.dist-info/WHEEL
crossref_local-0.4.0.dist-info/entry_points.txt
crossref_local-0.4.0.dist-info/RECORD
