Metadata-Version: 2.4
Name: crossref-local
Version: 0.4.0
Summary: Local CrossRef database with 167M+ works and full-text search
Project-URL: Homepage, https://github.com/ywatanabe1989/crossref_local
Project-URL: Repository, https://github.com/ywatanabe1989/crossref_local
Author: Yusuke Watanabe
License-Expression: AGPL-3.0
Keywords: academic,citations,crossref,doi,fts5,full-text-search,impact-factor,scholarly
Classifier: Development Status :: 4 - Beta
Classifier: Intended Audience :: Science/Research
Classifier: License :: OSI Approved :: GNU Affero General Public License v3
Classifier: Programming Language :: Python :: 3
Classifier: Programming Language :: Python :: 3.10
Classifier: Programming Language :: Python :: 3.11
Classifier: Programming Language :: Python :: 3.12
Classifier: Topic :: Database
Classifier: Topic :: Scientific/Engineering
Requires-Python: >=3.10
Requires-Dist: click>=8.0
Provides-Extra: all
Requires-Dist: fastapi>=0.100; extra == 'all'
Requires-Dist: fastmcp>=0.4; extra == 'all'
Requires-Dist: matplotlib>=3.7; extra == 'all'
Requires-Dist: networkx>=3.0; extra == 'all'
Requires-Dist: pytest-asyncio>=0.21; extra == 'all'
Requires-Dist: pytest-cov>=4.0; extra == 'all'
Requires-Dist: pytest>=7.0; extra == 'all'
Requires-Dist: pyvis>=0.3; extra == 'all'
Requires-Dist: uvicorn>=0.20; extra == 'all'
Provides-Extra: api
Requires-Dist: fastapi>=0.100; extra == 'api'
Requires-Dist: uvicorn>=0.20; extra == 'api'
Provides-Extra: dev
Requires-Dist: pytest-asyncio>=0.21; extra == 'dev'
Requires-Dist: pytest-cov>=4.0; extra == 'dev'
Requires-Dist: pytest>=7.0; extra == 'dev'
Provides-Extra: mcp
Requires-Dist: fastmcp>=0.4; extra == 'mcp'
Provides-Extra: viz
Requires-Dist: matplotlib>=3.7; extra == 'viz'
Requires-Dist: networkx>=3.0; extra == 'viz'
Requires-Dist: pyvis>=0.3; extra == 'viz'
